{"session": {"session_id": 1131, "state_id": 18, "year_start": 2015, "year_end": 2015, "prefile": 0, "sine_die": 1, "prior": 1, "special": 0, "session_tag": "Regular Session", "session_title": "2015 Regular Session", "session_name": "2015 Regular Session"}, "631": {"bill_id": 766806, "number": "HB632", "change_hash": "bf3d93aa05d8869bb27371fe09fdf277", "url": "https://legiscan.com/LA/bill/HB632/2015", "status_date": "2015-04-03", "status": 1, "last_action_date": "2015-04-13", "last_action": "Read by title, under the rules, referred to the Committee on Civil Law and Procedure.", "title": "Provides with respect to discrimination regarding sexual orientation, gender identity, and gender expression", "description": "Provides with respect to discrimination regarding sexual orientation, gender identity, and gender expression"}}